<?xml version="1.0" encoding="UTF-8"?>
<Settings>
    <Logging>
    	<!-- <Level>Warning</Level>  -->
    </Logging>
    <Broker>
        <Url>iot.eclipse.org</Url>
		<!-- <User>mqtt</User> -->
        <!-- <Password>password</Password> -->       
    </Broker>
    <Socket>
    	<!-- <NodeId>0</<NodeId> -->	
    </Socket>
    <Rf24>
    	<!-- <ChipSelect>0</ChipSelect> -->
        <!-- <ChipEnablePin>25</ChipEnablePin> -->
    	<!-- <IrqPin>24</IrqPin> -->
    	<!-- <Channel>10</Channel> -->		
    </Rf24>
</Settings>

